{
  "runInfo": {
    "numOnes": 787066,
    "numFreqItemsets": 174,
    "timestamp": "2023-05-11T11:22:19.067487981"
  },
  "convergenceStats": {
    "alice.samplers.AliceCSampler": [
      {
        "c90StepTime": 0,
        "totalTime": 157,
        "q3StepTime": 0,
        "avgRelFreqDiff": 0,
        "setupTime": 157,
        "maxStepTime": 0,
        "numSwapsFactor": 0,
        "minStepTime": 0,
        "q1StepTime": 0,
        "medianStepTime": 0,
        "c10StepTime": 0
      },
      {
        "c90StepTime": 0,
        "totalTime": 996,
        "q3StepTime": 0,
        "avgRelFreqDiff": 0.07460160846085587,
        "setupTime": 104,
        "maxStepTime": 5,
        "numSwapsFactor": 0.15,
        "minStepTime": 0,
        "q1StepTime": 0,
        "medianStepTime": 0,
        "c10StepTime": 0
      },
      {
        "c90StepTime": 0,
        "totalTime": 918,
        "q3StepTime": 0,
        "avgRelFreqDiff": 0.11799402003242991,
        "setupTime": 111,
        "maxStepTime": 1,
        "numSwapsFactor": 0.3,
        "minStepTime": 0,
        "q1StepTime": 0,
        "medianStepTime": 0,
        "c10StepTime": 0
      },
      {
        "c90StepTime": 0,
        "totalTime": 906,
        "q3StepTime": 0,
        "avgRelFreqDiff": 0.15913798391285408,
        "setupTime": 97,
        "maxStepTime": 1,
        "numSwapsFactor": 0.44999999999999996,
        "minStepTime": 0,
        "q1StepTime": 0,
        "medianStepTime": 0,
        "c10StepTime": 0
      },
      {
        "c90StepTime": 0,
        "totalTime": 898,
        "q3StepTime": 0,
        "avgRelFreqDiff": 0.18710232631118076,
        "setupTime": 98,
        "maxStepTime": 1,
        "numSwapsFactor": 0.6,
        "minStepTime": 0,
        "q1StepTime": 0,
        "medianStepTime": 0,
        "c10StepTime": 0
      },
      {
        "c90StepTime": 0,
        "totalTime": 908,
        "q3StepTime": 0,
        "avgRelFreqDiff": 0.20088339353451304,
        "setupTime": 107,
        "maxStepTime": 1,
        "numSwapsFactor": 0.75,
        "minStepTime": 0,
        "q1StepTime": 0,
        "medianStepTime": 0,
        "c10StepTime": 0
      },
      {
        "c90StepTime": 0,
        "totalTime": 899,
        "q3StepTime": 0,
        "avgRelFreqDiff": 0.2296279847921897,
        "setupTime": 100,
        "maxStepTime": 1,
        "numSwapsFactor": 0.9,
        "minStepTime": 0,
        "q1StepTime": 0,
        "medianStepTime": 0,
        "c10StepTime": 0
      },
      {
        "c90StepTime": 0,
        "totalTime": 887,
        "q3StepTime": 0,
        "avgRelFreqDiff": 0.26398254890867573,
        "setupTime": 92,
        "maxStepTime": 1,
        "numSwapsFactor": 1.05,
        "minStepTime": 0,
        "q1StepTime": 0,
        "medianStepTime": 0,
        "c10StepTime": 0
      },
      {
        "c90StepTime": 0,
        "totalTime": 930,
        "q3StepTime": 0,
        "avgRelFreqDiff": 0.2746499587638463,
        "setupTime": 101,
        "maxStepTime": 38,
        "numSwapsFactor": 1.2,
        "minStepTime": 0,
        "q1StepTime": 0,
        "medianStepTime": 0,
        "c10StepTime": 0
      },
      {
        "c90StepTime": 0,
        "totalTime": 772,
        "q3StepTime": 0,
        "avgRelFreqDiff": 0.2797015572113592,
        "setupTime": 88,
        "maxStepTime": 1,
        "numSwapsFactor": 1.3499999999999999,
        "minStepTime": 0,
        "q1StepTime": 0,
        "medianStepTime": 0,
        "c10StepTime": 0
      },
      {
        "c90StepTime": 0,
        "totalTime": 743,
        "q3StepTime": 0,
        "avgRelFreqDiff": 0.284207728926677,
        "setupTime": 70,
        "maxStepTime": 1,
        "numSwapsFactor": 1.4999999999999998,
        "minStepTime": 0,
        "q1StepTime": 0,
        "medianStepTime": 0,
        "c10StepTime": 0
      },
      {
        "c90StepTime": 0,
        "totalTime": 756,
        "q3StepTime": 0,
        "avgRelFreqDiff": 0.29841793258261085,
        "setupTime": 87,
        "maxStepTime": 1,
        "numSwapsFactor": 1.6499999999999997,
        "minStepTime": 0,
        "q1StepTime": 0,
        "medianStepTime": 0,
        "c10StepTime": 0
      },
      {
        "c90StepTime": 0,
        "totalTime": 751,
        "q3StepTime": 0,
        "avgRelFreqDiff": 0.3159887242724737,
        "setupTime": 82,
        "maxStepTime": 1,
        "numSwapsFactor": 1.7999999999999996,
        "minStepTime": 0,
        "q1StepTime": 0,
        "medianStepTime": 0,
        "c10StepTime": 0
      },
      {
        "c90StepTime": 0,
        "totalTime": 751,
        "q3StepTime": 0,
        "avgRelFreqDiff": 0.31981205042784316,
        "setupTime": 87,
        "maxStepTime": 1,
        "numSwapsFactor": 1.9499999999999995,
        "minStepTime": 0,
        "q1StepTime": 0,
        "medianStepTime": 0,
        "c10StepTime": 0
      },
      {
        "c90StepTime": 0,
        "totalTime": 305,
        "q3StepTime": 0,
        "avgRelFreqDiff": 0.32617899970698677,
        "setupTime": 82,
        "maxStepTime": 1,
        "numSwapsFactor": 2,
        "minStepTime": 0,
        "q1StepTime": 0,
        "medianStepTime": 0,
        "c10StepTime": 0
      },
      {
        "c90StepTime": 0,
        "totalTime": 4504,
        "q3StepTime": 0,
        "avgRelFreqDiff": 0.3842206250532283,
        "setupTime": 89,
        "maxStepTime": 1,
        "numSwapsFactor": 3,
        "minStepTime": 0,
        "q1StepTime": 0,
        "medianStepTime": 0,
        "c10StepTime": 0
      },
      {
        "c90StepTime": 0,
        "totalTime": 4484,
        "q3StepTime": 0,
        "avgRelFreqDiff": 0.4088829373463511,
        "setupTime": 76,
        "maxStepTime": 7,
        "numSwapsFactor": 4,
        "minStepTime": 0,
        "q1StepTime": 0,
        "medianStepTime": 0,
        "c10StepTime": 0
      },
      {
        "c90StepTime": 0,
        "totalTime": 4450,
        "q3StepTime": 0,
        "avgRelFreqDiff": 0.4287048486702581,
        "setupTime": 81,
        "maxStepTime": 1,
        "numSwapsFactor": 5,
        "minStepTime": 0,
        "q1StepTime": 0,
        "medianStepTime": 0,
        "c10StepTime": 0
      },
      {
        "c90StepTime": 0,
        "totalTime": 4426,
        "q3StepTime": 0,
        "avgRelFreqDiff": 0.43514486630154514,
        "setupTime": 81,
        "maxStepTime": 1,
        "numSwapsFactor": 6,
        "minStepTime": 0,
        "q1StepTime": 0,
        "medianStepTime": 0,
        "c10StepTime": 0
      },
      {
        "c90StepTime": 0,
        "totalTime": 4437,
        "q3StepTime": 0,
        "avgRelFreqDiff": 0.4507159451548884,
        "setupTime": 85,
        "maxStepTime": 6,
        "numSwapsFactor": 7,
        "minStepTime": 0,
        "q1StepTime": 0,
        "medianStepTime": 0,
        "c10StepTime": 0
      },
      {
        "c90StepTime": 0,
        "totalTime": 4409,
        "q3StepTime": 0,
        "avgRelFreqDiff": 0.4597781119416925,
        "setupTime": 75,
        "maxStepTime": 1,
        "numSwapsFactor": 8,
        "minStepTime": 0,
        "q1StepTime": 0,
        "medianStepTime": 0,
        "c10StepTime": 0
      },
      {
        "c90StepTime": 0,
        "totalTime": 4400,
        "q3StepTime": 0,
        "avgRelFreqDiff": 0.47565904169652595,
        "setupTime": 77,
        "maxStepTime": 1,
        "numSwapsFactor": 9,
        "minStepTime": 0,
        "q1StepTime": 0,
        "medianStepTime": 0,
        "c10StepTime": 0
      },
      {
        "c90StepTime": 0,
        "totalTime": 4536,
        "q3StepTime": 0,
        "avgRelFreqDiff": 0.4824468440133359,
        "setupTime": 86,
        "maxStepTime": 6,
        "numSwapsFactor": 10,
        "minStepTime": 0,
        "q1StepTime": 0,
        "medianStepTime": 0,
        "c10StepTime": 0
      },
      {
        "c90StepTime": 0,
        "totalTime": 4380,
        "q3StepTime": 0,
        "avgRelFreqDiff": 0.4937991610642052,
        "setupTime": 99,
        "maxStepTime": 1,
        "numSwapsFactor": 11,
        "minStepTime": 0,
        "q1StepTime": 0,
        "medianStepTime": 0,
        "c10StepTime": 0
      },
      {
        "c90StepTime": 0,
        "totalTime": 4350,
        "q3StepTime": 0,
        "avgRelFreqDiff": 0.4964894309734351,
        "setupTime": 87,
        "maxStepTime": 1,
        "numSwapsFactor": 12,
        "minStepTime": 0,
        "q1StepTime": 0,
        "medianStepTime": 0,
        "c10StepTime": 0
      },
      {
        "c90StepTime": 0,
        "totalTime": 4358,
        "q3StepTime": 0,
        "avgRelFreqDiff": 0.5063729966772089,
        "setupTime": 89,
        "maxStepTime": 1,
        "numSwapsFactor": 13,
        "minStepTime": 0,
        "q1StepTime": 0,
        "medianStepTime": 0,
        "c10StepTime": 0
      },
      {
        "c90StepTime": 0,
        "totalTime": 4366,
        "q3StepTime": 0,
        "avgRelFreqDiff": 0.5077639653403021,
        "setupTime": 74,
        "maxStepTime": 1,
        "numSwapsFactor": 14,
        "minStepTime": 0,
        "q1StepTime": 0,
        "medianStepTime": 0,
        "c10StepTime": 0
      },
      {
        "c90StepTime": 0,
        "totalTime": 4354,
        "q3StepTime": 0,
        "avgRelFreqDiff": 0.5158893616695032,
        "setupTime": 72,
        "maxStepTime": 1,
        "numSwapsFactor": 15,
        "minStepTime": 0,
        "q1StepTime": 0,
        "medianStepTime": 0,
        "c10StepTime": 0
      },
      {
        "c90StepTime": 0,
        "totalTime": 4361,
        "q3StepTime": 0,
        "avgRelFreqDiff": 0.5176798204905787,
        "setupTime": 81,
        "maxStepTime": 1,
        "numSwapsFactor": 16,
        "minStepTime": 0,
        "q1StepTime": 0,
        "medianStepTime": 0,
        "c10StepTime": 0
      },
      {
        "c90StepTime": 0,
        "totalTime": 4362,
        "q3StepTime": 0,
        "avgRelFreqDiff": 0.5247677634309666,
        "setupTime": 82,
        "maxStepTime": 1,
        "numSwapsFactor": 17,
        "minStepTime": 0,
        "q1StepTime": 0,
        "medianStepTime": 0,
        "c10StepTime": 0
      },
      {
        "c90StepTime": 0,
        "totalTime": 4380,
        "q3StepTime": 0,
        "avgRelFreqDiff": 0.526073281440563,
        "setupTime": 81,
        "maxStepTime": 1,
        "numSwapsFactor": 18,
        "minStepTime": 0,
        "q1StepTime": 0,
        "medianStepTime": 0,
        "c10StepTime": 0
      },
      {
        "c90StepTime": 0,
        "totalTime": 4391,
        "q3StepTime": 0,
        "avgRelFreqDiff": 0.5305015849426683,
        "setupTime": 78,
        "maxStepTime": 1,
        "numSwapsFactor": 19,
        "minStepTime": 0,
        "q1StepTime": 0,
        "medianStepTime": 0,
        "c10StepTime": 0
      },
      {
        "c90StepTime": 0,
        "totalTime": 4556,
        "q3StepTime": 0,
        "avgRelFreqDiff": 0.5377900078053256,
        "setupTime": 90,
        "maxStepTime": 7,
        "numSwapsFactor": 20,
        "minStepTime": 0,
        "q1StepTime": 0,
        "medianStepTime": 0,
        "c10StepTime": 0
      }
    ],
    "alice.samplers.GmmtSeqSampler": [
      {
        "c90StepTime": 0,
        "totalTime": 73,
        "q3StepTime": 0,
        "avgRelFreqDiff": 0,
        "setupTime": 73,
        "maxStepTime": 0,
        "numSwapsFactor": 0,
        "minStepTime": 0,
        "q1StepTime": 0,
        "medianStepTime": 0,
        "c10StepTime": 0
      },
      {
        "c90StepTime": 0,
        "totalTime": 143,
        "q3StepTime": 0,
        "avgRelFreqDiff": 0.008303986425418599,
        "setupTime": 72,
        "maxStepTime": 1,
        "numSwapsFactor": 0.15,
        "minStepTime": 0,
        "q1StepTime": 0,
        "medianStepTime": 0,
        "c10StepTime": 0
      },
      {
        "c90StepTime": 0,
        "totalTime": 136,
        "q3StepTime": 0,
        "avgRelFreqDiff": 0.016584943536011216,
        "setupTime": 73,
        "maxStepTime": 1,
        "numSwapsFactor": 0.3,
        "minStepTime": 0,
        "q1StepTime": 0,
        "medianStepTime": 0,
        "c10StepTime": 0
      },
      {
        "c90StepTime": 0,
        "totalTime": 134,
        "q3StepTime": 0,
        "avgRelFreqDiff": 0.019068716801839868,
        "setupTime": 72,
        "maxStepTime": 1,
        "numSwapsFactor": 0.44999999999999996,
        "minStepTime": 0,
        "q1StepTime": 0,
        "medianStepTime": 0,
        "c10StepTime": 0
      },
      {
        "c90StepTime": 0,
        "totalTime": 130,
        "q3StepTime": 0,
        "avgRelFreqDiff": 0.021309815395736953,
        "setupTime": 69,
        "maxStepTime": 1,
        "numSwapsFactor": 0.6,
        "minStepTime": 0,
        "q1StepTime": 0,
        "medianStepTime": 0,
        "c10StepTime": 0
      },
      {
        "c90StepTime": 0,
        "totalTime": 125,
        "q3StepTime": 0,
        "avgRelFreqDiff": 0.023548567574496776,
        "setupTime": 65,
        "maxStepTime": 1,
        "numSwapsFactor": 0.75,
        "minStepTime": 0,
        "q1StepTime": 0,
        "medianStepTime": 0,
        "c10StepTime": 0
      },
      {
        "c90StepTime": 0,
        "totalTime": 125,
        "q3StepTime": 0,
        "avgRelFreqDiff": 0.02601186691217484,
        "setupTime": 65,
        "maxStepTime": 1,
        "numSwapsFactor": 0.9,
        "minStepTime": 0,
        "q1StepTime": 0,
        "medianStepTime": 0,
        "c10StepTime": 0
      },
      {
        "c90StepTime": 0,
        "totalTime": 127,
        "q3StepTime": 0,
        "avgRelFreqDiff": 0.028188566448784206,
        "setupTime": 67,
        "maxStepTime": 1,
        "numSwapsFactor": 1.05,
        "minStepTime": 0,
        "q1StepTime": 0,
        "medianStepTime": 0,
        "c10StepTime": 0
      },
      {
        "c90StepTime": 0,
        "totalTime": 124,
        "q3StepTime": 0,
        "avgRelFreqDiff": 0.03026525412250134,
        "setupTime": 64,
        "maxStepTime": 1,
        "numSwapsFactor": 1.2,
        "minStepTime": 0,
        "q1StepTime": 0,
        "medianStepTime": 0,
        "c10StepTime": 0
      },
      {
        "c90StepTime": 0,
        "totalTime": 127,
        "q3StepTime": 0,
        "avgRelFreqDiff": 0.03794787179754294,
        "setupTime": 66,
        "maxStepTime": 1,
        "numSwapsFactor": 1.3499999999999999,
        "minStepTime": 0,
        "q1StepTime": 0,
        "medianStepTime": 0,
        "c10StepTime": 0
      },
      {
        "c90StepTime": 0,
        "totalTime": 130,
        "q3StepTime": 0,
        "avgRelFreqDiff": 0.03971941053730915,
        "setupTime": 70,
        "maxStepTime": 1,
        "numSwapsFactor": 1.4999999999999998,
        "minStepTime": 0,
        "q1StepTime": 0,
        "medianStepTime": 0,
        "c10StepTime": 0
      },
      {
        "c90StepTime": 0,
        "totalTime": 131,
        "q3StepTime": 0,
        "avgRelFreqDiff": 0.05286853434660989,
        "setupTime": 70,
        "maxStepTime": 1,
        "numSwapsFactor": 1.6499999999999997,
        "minStepTime": 0,
        "q1StepTime": 0,
        "medianStepTime": 0,
        "c10StepTime": 0
      },
      {
        "c90StepTime": 0,
        "totalTime": 136,
        "q3StepTime": 0,
        "avgRelFreqDiff": 0.05473909429698773,
        "setupTime": 75,
        "maxStepTime": 1,
        "numSwapsFactor": 1.7999999999999996,
        "minStepTime": 0,
        "q1StepTime": 0,
        "medianStepTime": 0,
        "c10StepTime": 0
      },
      {
        "c90StepTime": 0,
        "totalTime": 139,
        "q3StepTime": 0,
        "avgRelFreqDiff": 0.06193269283323705,
        "setupTime": 79,
        "maxStepTime": 1,
        "numSwapsFactor": 1.9499999999999995,
        "minStepTime": 0,
        "q1StepTime": 0,
        "medianStepTime": 0,
        "c10StepTime": 0
      },
      {
        "c90StepTime": 0,
        "totalTime": 101,
        "q3StepTime": 0,
        "avgRelFreqDiff": 0.06801445664240405,
        "setupTime": 78,
        "maxStepTime": 1,
        "numSwapsFactor": 2,
        "minStepTime": 0,
        "q1StepTime": 0,
        "medianStepTime": 0,
        "c10StepTime": 0
      },
      {
        "c90StepTime": 0,
        "totalTime": 459,
        "q3StepTime": 0,
        "avgRelFreqDiff": 0.10046808286261072,
        "setupTime": 78,
        "maxStepTime": 1,
        "numSwapsFactor": 3,
        "minStepTime": 0,
        "q1StepTime": 0,
        "medianStepTime": 0,
        "c10StepTime": 0
      },
      {
        "c90StepTime": 0,
        "totalTime": 456,
        "q3StepTime": 0,
        "avgRelFreqDiff": 0.11544044366991496,
        "setupTime": 79,
        "maxStepTime": 1,
        "numSwapsFactor": 4,
        "minStepTime": 0,
        "q1StepTime": 0,
        "medianStepTime": 0,
        "c10StepTime": 0
      },
      {
        "c90StepTime": 0,
        "totalTime": 454,
        "q3StepTime": 0,
        "avgRelFreqDiff": 0.12850519110540623,
        "setupTime": 79,
        "maxStepTime": 1,
        "numSwapsFactor": 5,
        "minStepTime": 0,
        "q1StepTime": 0,
        "medianStepTime": 0,
        "c10StepTime": 0
      },
      {
        "c90StepTime": 0,
        "totalTime": 462,
        "q3StepTime": 0,
        "avgRelFreqDiff": 0.13568809720792893,
        "setupTime": 84,
        "maxStepTime": 1,
        "numSwapsFactor": 6,
        "minStepTime": 0,
        "q1StepTime": 0,
        "medianStepTime": 0,
        "c10StepTime": 0
      },
      {
        "c90StepTime": 0,
        "totalTime": 459,
        "q3StepTime": 0,
        "avgRelFreqDiff": 0.14224137741877932,
        "setupTime": 84,
        "maxStepTime": 1,
        "numSwapsFactor": 7,
        "minStepTime": 0,
        "q1StepTime": 0,
        "medianStepTime": 0,
        "c10StepTime": 0
      },
      {
        "c90StepTime": 0,
        "totalTime": 446,
        "q3StepTime": 0,
        "avgRelFreqDiff": 0.14865212984663423,
        "setupTime": 75,
        "maxStepTime": 1,
        "numSwapsFactor": 8,
        "minStepTime": 0,
        "q1StepTime": 0,
        "medianStepTime": 0,
        "c10StepTime": 0
      },
      {
        "c90StepTime": 0,
        "totalTime": 440,
        "q3StepTime": 0,
        "avgRelFreqDiff": 0.16380992598269592,
        "setupTime": 71,
        "maxStepTime": 1,
        "numSwapsFactor": 9,
        "minStepTime": 0,
        "q1StepTime": 0,
        "medianStepTime": 0,
        "c10StepTime": 0
      },
      {
        "c90StepTime": 0,
        "totalTime": 435,
        "q3StepTime": 0,
        "avgRelFreqDiff": 0.16842023095949463,
        "setupTime": 70,
        "maxStepTime": 1,
        "numSwapsFactor": 10,
        "minStepTime": 0,
        "q1StepTime": 0,
        "medianStepTime": 0,
        "c10StepTime": 0
      },
      {
        "c90StepTime": 0,
        "totalTime": 436,
        "q3StepTime": 0,
        "avgRelFreqDiff": 0.17787946145810793,
        "setupTime": 71,
        "maxStepTime": 1,
        "numSwapsFactor": 11,
        "minStepTime": 0,
        "q1StepTime": 0,
        "medianStepTime": 0,
        "c10StepTime": 0
      },
      {
        "c90StepTime": 0,
        "totalTime": 438,
        "q3StepTime": 0,
        "avgRelFreqDiff": 0.18730719488343328,
        "setupTime": 75,
        "maxStepTime": 1,
        "numSwapsFactor": 12,
        "minStepTime": 0,
        "q1StepTime": 0,
        "medianStepTime": 0,
        "c10StepTime": 0
      },
      {
        "c90StepTime": 0,
        "totalTime": 436,
        "q3StepTime": 0,
        "avgRelFreqDiff": 0.19571826249098953,
        "setupTime": 72,
        "maxStepTime": 1,
        "numSwapsFactor": 13,
        "minStepTime": 0,
        "q1StepTime": 0,
        "medianStepTime": 0,
        "c10StepTime": 0
      },
      {
        "c90StepTime": 0,
        "totalTime": 442,
        "q3StepTime": 0,
        "avgRelFreqDiff": 0.2089334973771791,
        "setupTime": 78,
        "maxStepTime": 1,
        "numSwapsFactor": 14,
        "minStepTime": 0,
        "q1StepTime": 0,
        "medianStepTime": 0,
        "c10StepTime": 0
      },
      {
        "c90StepTime": 0,
        "totalTime": 439,
        "q3StepTime": 0,
        "avgRelFreqDiff": 0.22150958730228115,
        "setupTime": 79,
        "maxStepTime": 1,
        "numSwapsFactor": 15,
        "minStepTime": 0,
        "q1StepTime": 0,
        "medianStepTime": 0,
        "c10StepTime": 0
      },
      {
        "c90StepTime": 0,
        "totalTime": 434,
        "q3StepTime": 0,
        "avgRelFreqDiff": 0.22975007882843076,
        "setupTime": 74,
        "maxStepTime": 1,
        "numSwapsFactor": 16,
        "minStepTime": 0,
        "q1StepTime": 0,
        "medianStepTime": 0,
        "c10StepTime": 0
      },
      {
        "c90StepTime": 0,
        "totalTime": 431,
        "q3StepTime": 0,
        "avgRelFreqDiff": 0.2375012916079178,
        "setupTime": 72,
        "maxStepTime": 1,
        "numSwapsFactor": 17,
        "minStepTime": 0,
        "q1StepTime": 0,
        "medianStepTime": 0,
        "c10StepTime": 0
      },
      {
        "c90StepTime": 0,
        "totalTime": 429,
        "q3StepTime": 0,
        "avgRelFreqDiff": 0.24494868470029046,
        "setupTime": 70,
        "maxStepTime": 1,
        "numSwapsFactor": 18,
        "minStepTime": 0,
        "q1StepTime": 0,
        "medianStepTime": 0,
        "c10StepTime": 0
      },
      {
        "c90StepTime": 0,
        "totalTime": 431,
        "q3StepTime": 0,
        "avgRelFreqDiff": 0.24769259452585032,
        "setupTime": 72,
        "maxStepTime": 1,
        "numSwapsFactor": 19,
        "minStepTime": 0,
        "q1StepTime": 0,
        "medianStepTime": 0,
        "c10StepTime": 0
      },
      {
        "c90StepTime": 0,
        "totalTime": 433,
        "q3StepTime": 0,
        "avgRelFreqDiff": 0.2503272027299575,
        "setupTime": 74,
        "maxStepTime": 1,
        "numSwapsFactor": 20,
        "minStepTime": 0,
        "q1StepTime": 0,
        "medianStepTime": 0,
        "c10StepTime": 0
      }
    ]
  }
}
