{
  "runInfo": {
    "numOnes": 358278,
    "numFreqItemsets": 3683,
    "timestamp": "2023-05-06T22:30:16.150816"
  },
  "convergenceStats": {
    "alice.samplers.SelfLoopBJDMSampler": [
      {
        "c90StepTime": 0,
        "totalTime": 409,
        "q3StepTime": 0,
        "avgRelFreqDiff": 0,
        "setupTime": 409,
        "maxStepTime": 0,
        "numSwapsFactor": 0,
        "minStepTime": 0,
        "q1StepTime": 0,
        "medianStepTime": 0,
        "c10StepTime": 0
      },
      {
        "c90StepTime": 4,
        "totalTime": 208915,
        "q3StepTime": 4,
        "avgRelFreqDiff": 0.013499804163357026,
        "setupTime": 253,
        "maxStepTime": 584,
        "numSwapsFactor": 0.15,
        "minStepTime": 3,
        "q1StepTime": 3,
        "medianStepTime": 4,
        "c10StepTime": 3
      },
      {
        "c90StepTime": 5,
        "totalTime": 237176,
        "q3StepTime": 4,
        "avgRelFreqDiff": 0.029573129039198662,
        "setupTime": 261,
        "maxStepTime": 1604,
        "numSwapsFactor": 0.3,
        "minStepTime": 3,
        "q1StepTime": 4,
        "medianStepTime": 4,
        "c10StepTime": 3
      },
      {
        "c90StepTime": 4,
        "totalTime": 206370,
        "q3StepTime": 4,
        "avgRelFreqDiff": 0.04354713803808907,
        "setupTime": 237,
        "maxStepTime": 359,
        "numSwapsFactor": 0.44999999999999996,
        "minStepTime": 3,
        "q1StepTime": 3,
        "medianStepTime": 4,
        "c10StepTime": 3
      },
      {
        "c90StepTime": 4,
        "totalTime": 205043,
        "q3StepTime": 4,
        "avgRelFreqDiff": 0.05977098113070906,
        "setupTime": 232,
        "maxStepTime": 168,
        "numSwapsFactor": 0.6,
        "minStepTime": 3,
        "q1StepTime": 3,
        "medianStepTime": 3,
        "c10StepTime": 3
      },
      {
        "c90StepTime": 4,
        "totalTime": 204540,
        "q3StepTime": 4,
        "avgRelFreqDiff": 0.0713949185994955,
        "setupTime": 240,
        "maxStepTime": 181,
        "numSwapsFactor": 0.75,
        "minStepTime": 3,
        "q1StepTime": 3,
        "medianStepTime": 3,
        "c10StepTime": 3
      },
      {
        "c90StepTime": 4,
        "totalTime": 217372,
        "q3StepTime": 4,
        "avgRelFreqDiff": 0.09031417893040221,
        "setupTime": 195,
        "maxStepTime": 1421,
        "numSwapsFactor": 0.9,
        "minStepTime": 3,
        "q1StepTime": 3,
        "medianStepTime": 4,
        "c10StepTime": 3
      },
      {
        "c90StepTime": 4,
        "totalTime": 221475,
        "q3StepTime": 4,
        "avgRelFreqDiff": 0.1084101404754936,
        "setupTime": 196,
        "maxStepTime": 1500,
        "numSwapsFactor": 1.05,
        "minStepTime": 3,
        "q1StepTime": 3,
        "medianStepTime": 4,
        "c10StepTime": 3
      },
      {
        "c90StepTime": 4,
        "totalTime": 205824,
        "q3StepTime": 4,
        "avgRelFreqDiff": 0.12045885117707378,
        "setupTime": 217,
        "maxStepTime": 604,
        "numSwapsFactor": 1.2,
        "minStepTime": 3,
        "q1StepTime": 3,
        "medianStepTime": 4,
        "c10StepTime": 3
      },
      {
        "c90StepTime": 4,
        "totalTime": 221623,
        "q3StepTime": 4,
        "avgRelFreqDiff": 0.13089294173033292,
        "setupTime": 195,
        "maxStepTime": 1289,
        "numSwapsFactor": 1.3499999999999999,
        "minStepTime": 3,
        "q1StepTime": 3,
        "medianStepTime": 4,
        "c10StepTime": 3
      },
      {
        "c90StepTime": 4,
        "totalTime": 223808,
        "q3StepTime": 4,
        "avgRelFreqDiff": 0.1432931275277831,
        "setupTime": 200,
        "maxStepTime": 1171,
        "numSwapsFactor": 1.4999999999999998,
        "minStepTime": 3,
        "q1StepTime": 4,
        "medianStepTime": 4,
        "c10StepTime": 3
      },
      {
        "c90StepTime": 4,
        "totalTime": 208014,
        "q3StepTime": 4,
        "avgRelFreqDiff": 0.15230938950534215,
        "setupTime": 215,
        "maxStepTime": 1099,
        "numSwapsFactor": 1.6499999999999997,
        "minStepTime": 3,
        "q1StepTime": 3,
        "medianStepTime": 4,
        "c10StepTime": 3
      },
      {
        "c90StepTime": 4,
        "totalTime": 207312,
        "q3StepTime": 4,
        "avgRelFreqDiff": 0.16227561853111724,
        "setupTime": 212,
        "maxStepTime": 1254,
        "numSwapsFactor": 1.7999999999999996,
        "minStepTime": 3,
        "q1StepTime": 3,
        "medianStepTime": 3,
        "c10StepTime": 3
      },
      {
        "c90StepTime": 4,
        "totalTime": 207521,
        "q3StepTime": 4,
        "avgRelFreqDiff": 0.1743130463442109,
        "setupTime": 207,
        "maxStepTime": 1270,
        "numSwapsFactor": 1.9499999999999995,
        "minStepTime": 3,
        "q1StepTime": 3,
        "medianStepTime": 4,
        "c10StepTime": 3
      },
      {
        "c90StepTime": 4,
        "totalTime": 76228,
        "q3StepTime": 4,
        "avgRelFreqDiff": 0.1778588156871903,
        "setupTime": 199,
        "maxStepTime": 1175,
        "numSwapsFactor": 2,
        "minStepTime": 3,
        "q1StepTime": 4,
        "medianStepTime": 4,
        "c10StepTime": 3
      },
      {
        "c90StepTime": 4,
        "totalTime": 1543261,
        "q3StepTime": 4,
        "avgRelFreqDiff": 0.2340698788410597,
        "setupTime": 198,
        "maxStepTime": 1297,
        "numSwapsFactor": 3,
        "minStepTime": 3,
        "q1StepTime": 4,
        "medianStepTime": 4,
        "c10StepTime": 3
      },
      {
        "c90StepTime": 5,
        "totalTime": 1644382,
        "q3StepTime": 4,
        "avgRelFreqDiff": 0.28562104485690265,
        "setupTime": 207,
        "maxStepTime": 1547,
        "numSwapsFactor": 4,
        "minStepTime": 3,
        "q1StepTime": 4,
        "medianStepTime": 4,
        "c10StepTime": 4
      },
      {
        "c90StepTime": 5,
        "totalTime": 2452558,
        "q3StepTime": 4,
        "avgRelFreqDiff": 0.3300811038724273,
        "setupTime": 224,
        "maxStepTime": 978345,
        "numSwapsFactor": 5,
        "minStepTime": 3,
        "q1StepTime": 3,
        "medianStepTime": 4,
        "c10StepTime": 3
      }
    ],
    "alice.samplers.CurveballBJDMSampler": [
      {
        "c90StepTime": 0,
        "totalTime": 231,
        "q3StepTime": 0,
        "avgRelFreqDiff": 0,
        "setupTime": 231,
        "maxStepTime": 0,
        "numSwapsFactor": 0,
        "minStepTime": 0,
        "q1StepTime": 0,
        "medianStepTime": 0,
        "c10StepTime": 0
      },
      {
        "c90StepTime": 1,
        "totalTime": 9179,
        "q3StepTime": 0,
        "avgRelFreqDiff": 0.31669820891718053,
        "setupTime": 233,
        "maxStepTime": 65,
        "numSwapsFactor": 0.15,
        "minStepTime": 0,
        "q1StepTime": 0,
        "medianStepTime": 0,
        "c10StepTime": 0
      },
      {
        "c90StepTime": 1,
        "totalTime": 9208,
        "q3StepTime": 0,
        "avgRelFreqDiff": 0.5088137815476956,
        "setupTime": 275,
        "maxStepTime": 38,
        "numSwapsFactor": 0.3,
        "minStepTime": 0,
        "q1StepTime": 0,
        "medianStepTime": 0,
        "c10StepTime": 0
      },
      {
        "c90StepTime": 1,
        "totalTime": 9209,
        "q3StepTime": 0,
        "avgRelFreqDiff": 0.6244539313269734,
        "setupTime": 251,
        "maxStepTime": 36,
        "numSwapsFactor": 0.44999999999999996,
        "minStepTime": 0,
        "q1StepTime": 0,
        "medianStepTime": 0,
        "c10StepTime": 0
      },
      {
        "c90StepTime": 1,
        "totalTime": 9281,
        "q3StepTime": 0,
        "avgRelFreqDiff": 0.6954209837461652,
        "setupTime": 256,
        "maxStepTime": 33,
        "numSwapsFactor": 0.6,
        "minStepTime": 0,
        "q1StepTime": 0,
        "medianStepTime": 0,
        "c10StepTime": 0
      },
      {
        "c90StepTime": 1,
        "totalTime": 9424,
        "q3StepTime": 0,
        "avgRelFreqDiff": 0.7349959627361131,
        "setupTime": 264,
        "maxStepTime": 33,
        "numSwapsFactor": 0.75,
        "minStepTime": 0,
        "q1StepTime": 0,
        "medianStepTime": 0,
        "c10StepTime": 0
      },
      {
        "c90StepTime": 1,
        "totalTime": 9872,
        "q3StepTime": 0,
        "avgRelFreqDiff": 0.7596257026122633,
        "setupTime": 262,
        "maxStepTime": 36,
        "numSwapsFactor": 0.9,
        "minStepTime": 0,
        "q1StepTime": 0,
        "medianStepTime": 0,
        "c10StepTime": 0
      },
      {
        "c90StepTime": 1,
        "totalTime": 9446,
        "q3StepTime": 0,
        "avgRelFreqDiff": 0.7764725222632161,
        "setupTime": 263,
        "maxStepTime": 38,
        "numSwapsFactor": 1.05,
        "minStepTime": 0,
        "q1StepTime": 0,
        "medianStepTime": 0,
        "c10StepTime": 0
      },
      {
        "c90StepTime": 1,
        "totalTime": 9423,
        "q3StepTime": 0,
        "avgRelFreqDiff": 0.785396661813898,
        "setupTime": 282,
        "maxStepTime": 32,
        "numSwapsFactor": 1.2,
        "minStepTime": 0,
        "q1StepTime": 0,
        "medianStepTime": 0,
        "c10StepTime": 0
      },
      {
        "c90StepTime": 1,
        "totalTime": 927625,
        "q3StepTime": 0,
        "avgRelFreqDiff": 0.790775970693997,
        "setupTime": 279,
        "maxStepTime": 917641,
        "numSwapsFactor": 1.3499999999999999,
        "minStepTime": 0,
        "q1StepTime": 0,
        "medianStepTime": 0,
        "c10StepTime": 0
      },
      {
        "c90StepTime": 1,
        "totalTime": 9576,
        "q3StepTime": 0,
        "avgRelFreqDiff": 0.7950378500000621,
        "setupTime": 253,
        "maxStepTime": 39,
        "numSwapsFactor": 1.4999999999999998,
        "minStepTime": 0,
        "q1StepTime": 0,
        "medianStepTime": 0,
        "c10StepTime": 0
      },
      {
        "c90StepTime": 1,
        "totalTime": 9568,
        "q3StepTime": 0,
        "avgRelFreqDiff": 0.796917259214923,
        "setupTime": 258,
        "maxStepTime": 42,
        "numSwapsFactor": 1.6499999999999997,
        "minStepTime": 0,
        "q1StepTime": 0,
        "medianStepTime": 0,
        "c10StepTime": 0
      },
      {
        "c90StepTime": 1,
        "totalTime": 307857,
        "q3StepTime": 0,
        "avgRelFreqDiff": 0.7983179886647689,
        "setupTime": 258,
        "maxStepTime": 298115,
        "numSwapsFactor": 1.7999999999999996,
        "minStepTime": 0,
        "q1StepTime": 0,
        "medianStepTime": 0,
        "c10StepTime": 0
      },
      {
        "c90StepTime": 1,
        "totalTime": 9741,
        "q3StepTime": 0,
        "avgRelFreqDiff": 0.7993543410271309,
        "setupTime": 258,
        "maxStepTime": 38,
        "numSwapsFactor": 1.9499999999999995,
        "minStepTime": 0,
        "q1StepTime": 0,
        "medianStepTime": 0,
        "c10StepTime": 0
      },
      {
        "c90StepTime": 1,
        "totalTime": 3439,
        "q3StepTime": 0,
        "avgRelFreqDiff": 0.7996724270635763,
        "setupTime": 265,
        "maxStepTime": 36,
        "numSwapsFactor": 2,
        "minStepTime": 0,
        "q1StepTime": 0,
        "medianStepTime": 0,
        "c10StepTime": 0
      },
      {
        "c90StepTime": 1,
        "totalTime": 363153,
        "q3StepTime": 0,
        "avgRelFreqDiff": 0.8029709602462388,
        "setupTime": 266,
        "maxStepTime": 298105,
        "numSwapsFactor": 3,
        "minStepTime": 0,
        "q1StepTime": 0,
        "medianStepTime": 0,
        "c10StepTime": 0
      },
      {
        "c90StepTime": 1,
        "totalTime": 364723,
        "q3StepTime": 0,
        "avgRelFreqDiff": 0.8022472771250949,
        "setupTime": 283,
        "maxStepTime": 298084,
        "numSwapsFactor": 4,
        "minStepTime": 0,
        "q1StepTime": 0,
        "medianStepTime": 0,
        "c10StepTime": 0
      },
      {
        "c90StepTime": 1,
        "totalTime": 661405,
        "q3StepTime": 0,
        "avgRelFreqDiff": 0.8032014547435402,
        "setupTime": 272,
        "maxStepTime": 298638,
        "numSwapsFactor": 5,
        "minStepTime": 0,
        "q1StepTime": 0,
        "medianStepTime": 0,
        "c10StepTime": 0
      }
    ],
    "alice.samplers.BJDMSampler": [
      {
        "c90StepTime": 0,
        "totalTime": 286,
        "q3StepTime": 0,
        "avgRelFreqDiff": 0,
        "setupTime": 286,
        "maxStepTime": 0,
        "numSwapsFactor": 0,
        "minStepTime": 0,
        "q1StepTime": 0,
        "medianStepTime": 0,
        "c10StepTime": 0
      },
      {
        "c90StepTime": 0,
        "totalTime": 1404,
        "q3StepTime": 0,
        "avgRelFreqDiff": 0.11136984615638751,
        "setupTime": 262,
        "maxStepTime": 44,
        "numSwapsFactor": 0.15,
        "minStepTime": 0,
        "q1StepTime": 0,
        "medianStepTime": 0,
        "c10StepTime": 0
      },
      {
        "c90StepTime": 0,
        "totalTime": 1092,
        "q3StepTime": 0,
        "avgRelFreqDiff": 0.20038474361130443,
        "setupTime": 248,
        "maxStepTime": 36,
        "numSwapsFactor": 0.3,
        "minStepTime": 0,
        "q1StepTime": 0,
        "medianStepTime": 0,
        "c10StepTime": 0
      },
      {
        "c90StepTime": 0,
        "totalTime": 1252,
        "q3StepTime": 0,
        "avgRelFreqDiff": 0.2704679276797772,
        "setupTime": 240,
        "maxStepTime": 38,
        "numSwapsFactor": 0.44999999999999996,
        "minStepTime": 0,
        "q1StepTime": 0,
        "medianStepTime": 0,
        "c10StepTime": 0
      },
      {
        "c90StepTime": 0,
        "totalTime": 1274,
        "q3StepTime": 0,
        "avgRelFreqDiff": 0.33896669208652086,
        "setupTime": 242,
        "maxStepTime": 39,
        "numSwapsFactor": 0.6,
        "minStepTime": 0,
        "q1StepTime": 0,
        "medianStepTime": 0,
        "c10StepTime": 0
      },
      {
        "c90StepTime": 0,
        "totalTime": 1198,
        "q3StepTime": 0,
        "avgRelFreqDiff": 0.39368731827562775,
        "setupTime": 248,
        "maxStepTime": 1,
        "numSwapsFactor": 0.75,
        "minStepTime": 0,
        "q1StepTime": 0,
        "medianStepTime": 0,
        "c10StepTime": 0
      },
      {
        "c90StepTime": 0,
        "totalTime": 1154,
        "q3StepTime": 0,
        "avgRelFreqDiff": 0.4434435730821543,
        "setupTime": 243,
        "maxStepTime": 37,
        "numSwapsFactor": 0.9,
        "minStepTime": 0,
        "q1StepTime": 0,
        "medianStepTime": 0,
        "c10StepTime": 0
      },
      {
        "c90StepTime": 0,
        "totalTime": 1168,
        "q3StepTime": 0,
        "avgRelFreqDiff": 0.4869003951575254,
        "setupTime": 237,
        "maxStepTime": 37,
        "numSwapsFactor": 1.05,
        "minStepTime": 0,
        "q1StepTime": 0,
        "medianStepTime": 0,
        "c10StepTime": 0
      },
      {
        "c90StepTime": 0,
        "totalTime": 1097,
        "q3StepTime": 0,
        "avgRelFreqDiff": 0.5237258752387576,
        "setupTime": 240,
        "maxStepTime": 40,
        "numSwapsFactor": 1.2,
        "minStepTime": 0,
        "q1StepTime": 0,
        "medianStepTime": 0,
        "c10StepTime": 0
      },
      {
        "c90StepTime": 0,
        "totalTime": 1303,
        "q3StepTime": 0,
        "avgRelFreqDiff": 0.551330771495043,
        "setupTime": 252,
        "maxStepTime": 36,
        "numSwapsFactor": 1.3499999999999999,
        "minStepTime": 0,
        "q1StepTime": 0,
        "medianStepTime": 0,
        "c10StepTime": 0
      },
      {
        "c90StepTime": 0,
        "totalTime": 1068,
        "q3StepTime": 0,
        "avgRelFreqDiff": 0.5757336383547854,
        "setupTime": 276,
        "maxStepTime": 1,
        "numSwapsFactor": 1.4999999999999998,
        "minStepTime": 0,
        "q1StepTime": 0,
        "medianStepTime": 0,
        "c10StepTime": 0
      },
      {
        "c90StepTime": 0,
        "totalTime": 1199,
        "q3StepTime": 0,
        "avgRelFreqDiff": 0.5993676463520979,
        "setupTime": 239,
        "maxStepTime": 38,
        "numSwapsFactor": 1.6499999999999997,
        "minStepTime": 0,
        "q1StepTime": 0,
        "medianStepTime": 0,
        "c10StepTime": 0
      },
      {
        "c90StepTime": 0,
        "totalTime": 1059,
        "q3StepTime": 0,
        "avgRelFreqDiff": 0.6224476545876713,
        "setupTime": 259,
        "maxStepTime": 1,
        "numSwapsFactor": 1.7999999999999996,
        "minStepTime": 0,
        "q1StepTime": 0,
        "medianStepTime": 0,
        "c10StepTime": 0
      },
      {
        "c90StepTime": 0,
        "totalTime": 1264,
        "q3StepTime": 0,
        "avgRelFreqDiff": 0.6372041618078288,
        "setupTime": 242,
        "maxStepTime": 40,
        "numSwapsFactor": 1.9499999999999995,
        "minStepTime": 0,
        "q1StepTime": 0,
        "medianStepTime": 0,
        "c10StepTime": 0
      },
      {
        "c90StepTime": 0,
        "totalTime": 560,
        "q3StepTime": 0,
        "avgRelFreqDiff": 0.643308765193834,
        "setupTime": 247,
        "maxStepTime": 34,
        "numSwapsFactor": 2,
        "minStepTime": 0,
        "q1StepTime": 0,
        "medianStepTime": 0,
        "c10StepTime": 0
      },
      {
        "c90StepTime": 0,
        "totalTime": 5865,
        "q3StepTime": 0,
        "avgRelFreqDiff": 0.7169772042136194,
        "setupTime": 245,
        "maxStepTime": 35,
        "numSwapsFactor": 3,
        "minStepTime": 0,
        "q1StepTime": 0,
        "medianStepTime": 0,
        "c10StepTime": 0
      },
      {
        "c90StepTime": 0,
        "totalTime": 5876,
        "q3StepTime": 0,
        "avgRelFreqDiff": 0.7525988147880109,
        "setupTime": 251,
        "maxStepTime": 34,
        "numSwapsFactor": 4,
        "minStepTime": 0,
        "q1StepTime": 0,
        "medianStepTime": 0,
        "c10StepTime": 0
      },
      {
        "c90StepTime": 0,
        "totalTime": 6066,
        "q3StepTime": 0,
        "avgRelFreqDiff": 0.7741369073914224,
        "setupTime": 246,
        "maxStepTime": 37,
        "numSwapsFactor": 5,
        "minStepTime": 0,
        "q1StepTime": 0,
        "medianStepTime": 0,
        "c10StepTime": 0
      }
    ]
  }
}
